{
 "images": [
  {
   "file": "./Examples/aa.jpeg",
   "max_detection_conf": 0.999,
   "detections": [
    {
     "category": "1",
     "conf": 0.999,
     "bbox": [
      0.01144,
      0.2809,
      0.7878,
      0.6896
     ]
    },
    {
     "category": "1",
     "conf": 0.999,
     "bbox": [
      0.7349,
      0.5226,
      0.2079,
      0.1907
     ]
    },
    {
     "category": "1",
     "conf": 0.519,
     "bbox": [
      0.01917,
      0.6378,
      0.2832,
      0.3126
     ]
    },
    {
     "category": "1",
     "conf": 0.51,
     "bbox": [
      0,
      0.5577,
      0.07302,
      0.2648
     ]
    },
    {
     "category": "1",
     "conf": 0.317,
     "bbox": [
      0.0782,
      0.7244,
      0.2169,
      0.2282
     ]
    },
    {
     "category": "1",
     "conf": 0.186,
     "bbox": [
      0.0001482,
      0.5561,
      0.1037,
      0.354
     ]
    },
    {
     "category": "1",
     "conf": 0.152,
     "bbox": [
      0,
      0.5292,
      0.198,
      0.4036
     ]
    }
   ]
  }
 ],
 "detection_categories": {
  "1": "animal",
  "2": "person",
  "4": "vehicle"
 },
 "info": {
  "detection_completion_time": "2020-03-10 17:17:09",
  "format_version": "1.0"
 }
}